vision_explanation_methods/DRISE_runner.py
vision_explanation_methods/__init__.py
vision_explanation_methods/version.py
vision_explanation_methods/error_labeling/__init__.py
vision_explanation_methods/error_labeling/error_labeling.py
vision_explanation_methods/evaluation/__init__.py
vision_explanation_methods/evaluation/pointing_game.py
vision_explanation_methods/explanations/__init__.py
vision_explanation_methods/explanations/common.py
vision_explanation_methods/explanations/drise.py
vision_explanation_methods-0.1.1.dist-info/LICENSE.txt
vision_explanation_methods-0.1.1.dist-info/METADATA
vision_explanation_methods-0.1.1.dist-info/WHEEL
vision_explanation_methods-0.1.1.dist-info/top_level.txt
vision_explanation_methods-0.1.1.dist-info/RECORD
