Metadata-Version: 2.1
Name: vision-explanation-methods
Version: 0.1.1
Summary: Microsoft Vision Explanation Methods SDK for Python
Home-page: https://github.com/microsoft/vision-explanation-methods
Author: Microsoft Corp
Author-email: jamhall@microsoft.com
License: MIT License
Classifier: Development Status :: 5 - Production/Stable
Classifier: Intended Audience :: Developers
Classifier: Intended Audience :: Science/Research
Classifier: License :: OSI Approved :: MIT License
Classifier: Programming Language :: Python :: 3
Classifier: Programming Language :: Python :: 3.7
Classifier: Programming Language :: Python :: 3.8
Classifier: Programming Language :: Python :: 3.9
Classifier: Topic :: Scientific/Engineering :: Artificial Intelligence
Classifier: Operating System :: Microsoft :: Windows
Classifier: Operating System :: MacOS
Classifier: Operating System :: POSIX :: Linux
License-File: LICENSE.txt
Requires-Dist: numpy
Requires-Dist: tqdm
Requires-Dist: matplotlib <3.7.0
Requires-Dist: ml-wrappers
